{
  "project_info": {
    "project_number": "77770924184",
    "firebase_url": "https://novamoda-3dcc9-default-rtdb.firebaseio.com",
    "project_id": "novamoda-3dcc9",
    "storage_bucket": "novamoda-3dcc9.appspot.com"
  },
  "client": [
    {
      "client_info": {
        "mobilesdk_app_id": "1:77770924184:android:a3f178464899ddefbff0ed",
        "android_client_info": {
          "package_name": "com.holeCode.novamoda"
        }
      },
      "oauth_client": [
        {
          "client_id": "77770924184-b3ub85156uftlaa2imjm2gt5irtoo9m5.apps.googleusercontent.com",
          "client_type": 1,
          "android_info": {
            "package_name": "com.holeCode.novamoda",
            "certificate_hash": "3bd4ff9aed771c25971a58219bd1799b4e404092"
          }
        },
        {
          "client_id": "77770924184-jamh047c6hbtjug0tbjvn9ucsul0vntv.apps.googleusercontent.com",
          "client_type": 3
        }
      ],
      "api_key": [
        {
          "current_key": "AIzaSyC3_EXetbNwcVJvXhcf8c0VzV1I3AIKXMI"
        }
      ],
      "services": {
        "appinvite_service": {
          "other_platform_oauth_client": [
            {
              "client_id": "77770924184-jamh047c6hbtjug0tbjvn9ucsul0vntv.apps.googleusercontent.com",
              "client_type": 3
            }
          ]
        }
      }
    }
  ],
  "configuration_version": "1"
}